MANIFEST.in
README.md
setup.py
bin/arduino-udev-name
firmware/UDEV/UDEV.cpp
firmware/UDEV/UDEV.h
firmware/example/Makefile
firmware/example/firmware.ino
firmware/example2/Makefile
firmware/example2/example2.py
firmware/example2/firmware.ino
src/arduinoudev.py
src/arduino_udev.egg-info/PKG-INFO
src/arduino_udev.egg-info/SOURCES.txt
src/arduino_udev.egg-info/dependency_links.txt
src/arduino_udev.egg-info/top_level.txt
udev/99-arduino-udev.rules